alpha_vantage/__init__.py
alpha_vantage/__version__.py
alpha_vantage/client.py
alpha_vantage/functions/__init__.py
alpha_vantage/functions/timeseries.py
alpha_vantage/models/__init__.py
alpha_vantage/models/exceptions.py
alpha_vantage/models/timeseries.py
tests/__init__.py
tests/test_client.py
tests/functions/__init__.py
tests/functions/test_timeseries.py
alpha_vantage_py-0.0.5.dist-info/LICENSE
alpha_vantage_py-0.0.5.dist-info/METADATA
alpha_vantage_py-0.0.5.dist-info/WHEEL
alpha_vantage_py-0.0.5.dist-info/top_level.txt
alpha_vantage_py-0.0.5.dist-info/RECORD
