Metadata-Version: 2.1
Name: alpha-vantage-py
Version: 0.0.5
Summary: Alpha Vantage Python package.
Home-page: https://github.com/wstolk/alpha-vantage
Author: Wouter Stolk
Author-email: stolk.wouter@gmail.com
License: Apache 2.0
Project-URL: Source, https://github.com/wstolk/alpha-vantage
Project-URL: Documentation, https://alpha-vantage-py.readthedocs.io/en/latest/
Platform: UNKNOWN
Classifier: License :: OSI Approved :: Apache Software License
Classifier: Programming Language :: Python
Classifier: Programming Language :: Python :: 2
Classifier: Programming Language :: Python :: 3
Requires-Python: >=3.6
Requires-Dist: requests (>=2)
